uts46/__init__.py
uts46/_data.py
uts46/_datamodels.py
uts46/_errors.py
uts46/_idna2008.py
uts46/_rangemap.py
uts46/_uts46_internal.py
uts46/_version.py
uts46/codecs.py
uts46/py.typed
uts46/uts46.py
uts46/whatwg.py
uts46-0.2.0.dist-info/METADATA
uts46-0.2.0.dist-info/WHEEL
uts46-0.2.0.dist-info/licenses/LICENSE
uts46-0.2.0.dist-info/RECORD
