Metadata-Version: 2.4
Name: uts46
Version: 0.2.0
Summary: UTS46 Unicode IDNA Compatibility Processing
Project-URL: Homepage, https://github.com/medmunds/uts46
Project-URL: Bug Tracker, https://github.com/medmunds/uts46/issues
Author-email: Mike Edmunds <medmunds@gmail.com>
License-File: LICENSE
Keywords: IDN,IDNA,IDNA Compatibility Processing,IDNA2008 preprocessing,Punycode,UTS-46,UTS46,Unicode,WHATWG URL Standard,internationalized domain names
Classifier: Development Status :: 3 - Alpha
Classifier: Intended Audience :: Developers
Classifier: License :: OSI Approved :: MIT License
Classifier: Operating System :: OS Independent
Classifier: Programming Language :: Python :: 3
Classifier: Topic :: Internet :: Name Service (DNS)
Classifier: Topic :: Software Development :: Libraries :: Python Modules
Classifier: Topic :: Text Processing :: General
Classifier: Typing :: Typed
Requires-Python: >=3.10
Provides-Extra: dev
Requires-Dist: mypy~=1.15.0; extra == 'dev'
Requires-Dist: pre-commit~=4.1.0; extra == 'dev'
Requires-Dist: ruff~=0.9.10; extra == 'dev'
Requires-Dist: tomli; (python_version < '3.11') and extra == 'dev'
Provides-Extra: lint
Requires-Dist: mypy~=1.15.0; extra == 'lint'
Requires-Dist: ruff~=0.9.10; extra == 'lint'
Provides-Extra: test
